summarizer/extension.py
summarizer/cli.py
summarizer/chatgpt.py
summarizer/summarizer.py
summarizer/libnative.so
summarizer/__init__.py
summarizer/audio_decode.c
summarizer/huggingchat.py
summarizer/template.html
llama_summarizer-0.1.5.dist-info/RECORD
llama_summarizer-0.1.5.dist-info/entry_points.txt
llama_summarizer-0.1.5.dist-info/WHEEL
llama_summarizer-0.1.5.dist-info/METADATA
llama_summarizer-0.1.5.dist-info/licenses/LICENSE
llama_summarizer.libs/libswscale-7848627b.so.8.1.100
llama_summarizer.libs/libopus-cedd2387.so.0.9.0
llama_summarizer.libs/libavformat-bc3558be.so.61.1.100
llama_summarizer.libs/libswresample-e97774d8.so.5.1.100
llama_summarizer.libs/libavcodec-6c2864b8.so.61.3.100
llama_summarizer.libs/libavutil-21221c0c.so.59.8.100
llama_summarizer.libs/libdrm-49e75d1e.so.2.4.0
llama_summarizer.libs/libavfilter-78fb532b.so.10.1.100
