Metadata-Version: 2.1
Name: llama-summarizer
Version: 0.1.5
Requires-Python: >=3.11
Requires-Dist: Jinja2>=3.1.3
Requires-Dist: llama_cpp_python>=0.2.64
Requires-Dist: requests>=2.31.0
Requires-Dist: yt-dlp>=2024.4.9
Requires-Dist: huggingface_hub>=0.22.1
Requires-Dist: whisper-cpp-python-smr>=0.1
